{
  "recipes": [
    {
      "image": "https://i.ytimg.com/vi/1P6fXQSdk1w/maxresdefault.jpg",
      "recipe_Name": "chicken and dumplings",
      "by": "lee",
      "scope": "",
      "recipe_Type": "dinner",
      "degree_Units": "",
      "prep_Time": "300 mins",
      "cook_Time": "400 mins",
      "cook_Temp": 300,
      "portion_Amount": 1,
      "portion_Type": "loaves",
      "personal_Notes": "its a pain the ass. go around the other way. it just takes a s long. i know the exits there are real far apart",
      "id": 1
    },
    {
      "image": "http://www.fmbpune.com/wp-content/uploads/2015/07/grilled-teriyaki-fish-en-f2afbef5-2cb6-4e83-941b-94f745b605671.jpg",
      "recipe_Name": "Grilled victory salmon",
      "by": "carrie",
      "scope": "",
      "recipe_Type": "dessert",
      "degree_Units": "",
      "prep_Time": "forever",
      "cook_Time": "min",
      "cook_Temp": 50,
      "portion_Amount": 2,
      "portion_Type": "fishies",
      "personal_Notes": "pleae be right",
      "id": 2
    },
    {
      "image": "https://reckittbenckiser.calcmenuweb.com/picNormal/lg_11383.jpg",
      "recipe_Name": "Buffalo Chicken Wrap",
      "by": "Carrie",
      "scope": {
        "isTrusted": false
      },
      "recipe_Type": "dinner",
      "degree_Units": "",
      "prep_Time": 20,
      "cook_Time": 20,
      "cook_Temp": 0,
      "portion_Amount": 1,
      "portion_Type": "serving",
      "personal_Notes": "eat",
      "id": 3
    }
  ],
  "steps": [
    {
      "recipeId": 1,
      "directions": "bake",
      "id": 1
    },
    {
      "recipeId": 1,
      "directions": "broil",
      "id": 2
    },
    {
      "recipeId": 1,
      "directions": "fry",
      "id": 3
    },
    {
      "recipeId": 1,
      "directions": "sautee",
      "id": 4
    },
    {
      "recipeId": 2,
      "directions": "broil",
      "id": 5
    },
    {
      "recipeId": 2,
      "directions": "bake",
      "id": 6
    },
    {
      "recipeId": 2,
      "directions": "fry",
      "id": 7
    },
    {
      "recipeId": 2,
      "directions": "dismember",
      "id": 8
    },
    {
      "recipeId": 2,
      "directions": "blend",
      "id": 9
    },
    {
      "recipeId": 2,
      "directions": "vacuum pack",
      "id": 10
    },
    {
      "recipeId": 3,
      "directions": "cook chicken",
      "id": 11
    },
    {
      "recipeId": 3,
      "directions": "add sauce",
      "id": 12
    },
    {
      "recipeId": 3,
      "directions": "wrap chicken",
      "id": 13
    },
    {
      "recipeId": 4,
      "directions": "",
      "id": 14
    },
    {
      "recipeId": 4,
      "directions": "",
      "id": 15
    }
  ],
  "auis": [
    {
      "stepId": 1,
      "ingredient": "steak",
      "units": "packets",
      "step_Amount": "3 ",
      "recipeId": 1,
      "id": 1
    },
    {
      "stepId": 2,
      "ingredient": "carrots",
      "units": "units",
      "step_Amount": 25,
      "recipeId": 1,
      "id": 2
    },
    {
      "stepId": 3,
      "ingredient": "dough",
      "units": "dozen",
      "step_Amount": 1,
      "recipeId": 1,
      "id": 3
    },
    {
      "stepId": 4,
      "ingredient": "onion",
      "units": "whole",
      "step_Amount": 1,
      "recipeId": 1,
      "id": 4
    },
    {
      "stepId": 5,
      "ingredient": "lemon",
      "units": "half",
      "step_Amount": 1,
      "recipeId": 2,
      "id": 5
    },
    {
      "stepId": 6,
      "ingredient": "potatoes",
      "units": "whole",
      "step_Amount": 2,
      "recipeId": 2,
      "id": 6
    },
    {
      "stepId": 7,
      "ingredient": "bacon",
      "units": "lb",
      "step_Amount": 1,
      "recipeId": 2,
      "id": 7
    },
    {
      "stepId": 8,
      "ingredient": "of fish",
      "units": "head",
      "step_Amount": 1,
      "recipeId": 2,
      "id": 8
    },
    {
      "stepId": 9,
      "ingredient": "salmon",
      "units": "tail",
      "step_Amount": 1,
      "recipeId": 2,
      "id": 9
    },
    {
      "stepId": 10,
      "ingredient": "eyes",
      "units": "fish",
      "step_Amount": "3 ",
      "recipeId": 2,
      "id": 10
    },
    {
      "stepId": 11,
      "ingredient": "chicken",
      "units": "lb",
      "step_Amount": 1,
      "recipeId": 3,
      "id": 11
    },
    {
      "stepId": 12,
      "ingredient": "hot sauce",
      "units": "bottle",
      "step_Amount": 1,
      "recipeId": 3,
      "id": 12
    },
    {
      "stepId": 13,
      "ingredient": "tortilla",
      "units": "whole",
      "step_Amount": 1,
      "recipeId": 3,
      "id": 13
    },
    {
      "stepId": 14,
      "ingredient": 1,
      "units": 1,
      "step_Amount": 11,
      "recipeId": 4,
      "id": 14
    }
  ]
}